_tsinfer.cpython-312-x86_64-linux-gnu.so
tsinfer/__init__.py
tsinfer/__main__.py
tsinfer/_version.py
tsinfer/algorithm.py
tsinfer/ancestors.py
tsinfer/cli.py
tsinfer/constants.py
tsinfer/eval_util.py
tsinfer/exceptions.py
tsinfer/formats.py
tsinfer/inference.py
tsinfer/progress.py
tsinfer/provenance.py
tsinfer/threads.py
tsinfer-0.5.0.dist-info/METADATA
tsinfer-0.5.0.dist-info/WHEEL
tsinfer-0.5.0.dist-info/entry_points.txt
tsinfer-0.5.0.dist-info/top_level.txt
tsinfer-0.5.0.dist-info/RECORD
tsinfer-0.5.0.dist-info/licenses/LICENSE
